setup.cfg
setup.py
gpapi/__init__.py
gpapi/config.py
gpapi/device.properties
gpapi/googleplay.py
gpapi/googleplay_pb2.py
gpapi/utils.py
gplayapi.egg-info/PKG-INFO
gplayapi.egg-info/SOURCES.txt
gplayapi.egg-info/dependency_links.txt
gplayapi.egg-info/requires.txt
gplayapi.egg-info/top_level.txt