Metadata-Version: 1.0
Name: gplayapi
Version: 0.2.1
Summary: Unofficial python api for google play
Home-page: https://github.com/matlink/googleplay-api
Author: Matlink
Author-email: matlink@matlink.fr
License: MIT
Platform: UNKNOWN
